[
  {
    "lesson_id": "065",
    "trigger_word": "an|machen",
    "trigger_card_number": 2820,
    "title": "LESSON 65: EVERYDAY GERMAN PHRASES",
    "header_color": "cyan",
    "pages": [
      {
        "page": 1,
        "total_pages": 2,
        "content": [
          "Real German life phrases you'll see everywhere:",
          "",
          "MAILBOX & DOOR SIGNS:",
          "Keine Werbung (No advertisements/junk mail)",
          "Kein Einwurf (No entry - for mail)",
          "Briefkasten (Mailbox)",
          "",
          "NEIGHBOR CULTURE:",
          "Ihr Paket liegt beim Nachbarn.",
          "(Your package is with the neighbor)",
          "",
          "Bitte klingeln Sie bei Müller.",
          "(Please ring at Müller's)",
          "",
          "APARTMENT PHRASES:",
          "Kalt (Cold water included in rent)",
          "Warm (Utilities included)",
          "Kaution (Deposit)",
          "Nebenkosten (Additional costs/utilities)",
          "",
          "Ruhezeiten beachten (Observe quiet hours)",
          "Usually: 13:00-15:00 and 22:00-07:00"
        ],
        "pronunciation": "Lektion 65"
      },
      {
        "page": 2,
        "total_pages": 2,
        "content": [
          "SHOPPING & SIGNS:",
          "Kasse (Checkout/cashier)",
          "Reduziert (Reduced/on sale)",
          "Aktion/Angebot (Special offer/deal)",
          "Geschlossen (Closed)",
          "Geöffnet (Open)",
          "",
          "RESTAURANT BASICS:",
          "Reservierung (Reservation)",
          "Stammtisch (Reserved table for regulars)",
          "Getrennt oder zusammen?",
          "(Separate bills or together?)",
          "",
          "Zum Mitnehmen (To take away)",
          "Zum Hieressen (To eat here)",
          "Mit Karte (Pay by card)",
          "",
          "Selbstbedienung (Self-service)",
          "",
          "VERY GERMAN:",
          "Feierabend (End of workday - sacred time!)",
          "Zum Wohl! / Prost! (Cheers!)"
        ]
      }
    ]
  },
  {
    "lesson_id": "066",
    "trigger_word": "Naturwissenschaft",
    "trigger_card_number": 2900,
    "title": "LESSON 66: MEMORABLE GERMAN WORDS",
    "header_color": "cyan",
    "pages": [
      {
        "page": 1,
        "total_pages": 2,
        "content": [
          "Words you'll never forget because they're",
          "funny, weird, or perfectly German:",
          "",
          "BODY PARTS YOU'LL REMEMBER:",
          "die Brustwarze (nipple - 'breast wart')",
          "das Zahnfleisch (gums - 'tooth meat')",
          "die Armbeuge (elbow pit - 'arm bend')",
          "",
          "PERFECTLY LITERAL COMPOUNDS:",
          "das Handschuh (glove - 'hand shoe')",
          "die Fußgängerzone (pedestrian zone)",
          "die Barfußzone (barefoot zone)",
          "",
          "ANIMALS:",
          "das Stinktier (skunk - 'stink animal')",
          "das Faultier (sloth - 'lazy animal')",
          "die Nacktschnecke (slug - 'naked snail')",
          "der Seehund (seal - 'sea dog', also: die Robbe)"
        ],
        "pronunciation": "Lektion 66"
      },
      {
        "page": 2,
        "total_pages": 2,
        "content": [
          "INCREDIBLY LONG COMPOUNDS:",
          "die Donaudampfschifffahrtsgesellschaft",
          "(Danube steamship company)",
          "",
          "der Rindfleischetikettierungsüberwachungs-",
          "aufgabenübertragungsgesetz",
          "(Beef labeling supervision duty transfer law)",
          "",
          "verschlimmbessern (to make worse while",
          "trying to improve)",
          "",
          "die Steinschlagreparatur",
          "(windscreen crack repair - 'stone chip repair')",
          "",
          "der Eierschalensollbruchstellenverursacher",
          "(egg shell predetermined breaking point causer",
          "= egg cracker tool)"
        ]
      }
    ]
  },
  {
    "lesson_id": "067",
    "trigger_word": "übertragen",
    "trigger_card_number": 3000,
    "title": "LESSON 67: GERMAN INSULTS & BANTER",
    "header_color": "cyan",
    "pages": [
      {
        "page": 1,
        "total_pages": 2,
        "content": [
          "How Germans tease, joke, and (gently) insult:",
          "",
          "PLAYFUL INSULTS (among friends):",
          "Du Dicke! (You fatty! - often affectionate)",
          "Du Spinner! (You crazy person!)",
          "Quatschkopf (nonsense head - silly person)",
          "",
          "STRONGER (use carefully!):",
          "Arschloch (asshole)",
          "Arsch (ass)",
          "Idiot (idiot - stronger than English)",
          "Vollidiot (total idiot)",
          "",
          "ANIMAL COMPARISONS:",
          "Du Schwein! (You pig! - rude)",
          "Blöde Kuh! (Stupid cow! - very rude to women)",
          "Faule Sau! (Lazy pig! - very insulting)"
        ],
        "pronunciation": "Lektion 67"
      },
      {
        "page": 2,
        "total_pages": 2,
        "content": [
          "EXPRESSIONS OF FRUSTRATION:",
          "Scheiße! (Shit! - very common)",
          "Mist! (Darn! - milder)",
          "Verdammt! (Damn it!)",
          "Ach du Scheiße! (Oh shit!)",
          "Ach du meine Güte! (Oh my goodness! - polite)",
          "",
          "SURPRISE/DISBELIEF:",
          "Das gibt's doch nicht! (That can't be!)",
          "Ich glaub's nicht! (I don't believe it!)",
          "Spinnst du? (Are you crazy?)",
          "",
          "TELLING SOMEONE OFF:",
          "Halt die Klappe! (Shut up! - rude)",
          "Lass mich in Ruhe! (Leave me alone!)",
          "",
          "Remember: Germans are direct, but context",
          "matters! These range from playful to offensive.",
          "Use Du Spinner! with friends, not your boss!"
        ]
      }
    ]
  }
]