{
  "shared": [
    {"image": "../screenshots/common/entrance.png", "key": "*", "title": "Welcome to FlashBoss"},
    {"image": "unsorted images/first.png", "key": "1", "title": "First Time User"},
    {"image": "../screenshots/common/create-username.png", "key": "↵", "title": "Create Username"},
    {"image": "../screenshots/common/create avatar.png", "key": "1-8", "title": "Choose Avatar"},
    {"image": "../screenshots/common/create-master1.png", "key": "1-6", "title": "Choose Master"},
    {"image": "../screenshots/common/create-pack.png", "key": null, "title": "Choose Language Pack", "fork": true}
  ],
  "esperanto": [
    {"image": "images/esperanto/01_screenshot.png", "key": "*", "title": "Esperanto Path"},
    {"image": "images/esperanto/02_screenshot.png", "key": "*", "title": "Esperanto Path"},
    {"image": "images/esperanto/03_screenshot.png", "key": "*", "title": "Esperanto Path"},
    {"image": "images/esperanto/04_screenshot.png", "key": "*", "title": "Esperanto Path"},
    {"image": "images/esperanto/05_screenshot.png", "key": "*", "title": "Esperanto Path"},
    {"image": "images/esperanto/06_screenshot.png", "key": "*", "title": "Esperanto Path"},
    {"image": "images/esperanto/07_screenshot.png", "key": "*", "title": "Esperanto Path"},
    {"image": "images/esperanto/08_screenshot.png", "key": "*", "title": "Esperanto Path"},
    {"image": "images/esperanto/09_screenshot.png", "key": "*", "title": "Esperanto Path"},
    {"image": "images/esperanto/10_screenshot.png", "key": "*", "title": "Esperanto Path"},
    {"image": "images/esperanto/11_screenshot.png", "key": "*", "title": "Esperanto Path"},
    {"image": "images/esperanto/12_screenshot.png", "key": "*", "title": "Esperanto Path"},
    {"image": "images/esperanto/13_screenshot.png", "key": "*", "title": "Esperanto Path"},
    {"image": "images/esperanto/14_screenshot.png", "key": "*", "title": "Esperanto Path"},
    {"image": "images/esperanto/15_screenshot.png", "key": "*", "title": "Esperanto Path"},
    {"image": "images/esperanto/16_screenshot.png", "key": "*", "title": "Esperanto Path"},
    {"image": "images/esperanto/17_screenshot.png", "key": "*", "title": "Esperanto Path"},
    {"image": "images/esperanto/18_screenshot.png", "key": "*", "title": "Esperanto Path"},
    {"image": "images/esperanto/19_screenshot.png", "key": "*", "title": "Esperanto Path"},
    {"image": "images/esperanto/20_screenshot.png", "key": "*", "title": "Esperanto Path"},
    {"image": "images/esperanto/21_screenshot.png", "key": "*", "title": "Esperanto Path"},
    {"image": "images/esperanto/22_screenshot.png", "key": null, "title": "Walkthrough Complete", "end": true}
  ],
  "german": [
    {"image": "../screenshots/common/create-pack.png", "key": null, "title": "Choose Difficulty", "fork": "difficulty"}
  ],
  "german-core": [
    {"image": "german/promoDE1.2/03_screenshot.png", "key": "*", "title": "Core — 1.2 Numbers & Time"},
    {"image": "german/promoDE1.2/04_screenshot.png", "key": "*", "title": "Core — 1.2 Numbers & Time"},
    {"image": "german/promoDE1.2/05_screenshot.png", "key": "*", "title": "Core — 1.2 Numbers & Time"},
    {"image": "german/promoDE1.2/06_screenshot.png", "key": "*", "title": "Core — 1.2 Numbers & Time"},
    {"image": "german/promoDE1.2/07_screenshot.png", "key": "*", "title": "Core — 1.2 Numbers & Time"},
    {"image": "german/promoDE1.2/08_screenshot.png", "key": "*", "title": "Core — 1.2 Numbers & Time"},
    {"image": "german/promoDE1.2/09_screenshot.png", "key": "*", "title": "Core — 1.2 Numbers & Time"},
    {"image": "german/promoDE1.2/10_screenshot.png", "key": "*", "title": "Core — 1.2 Numbers & Time"},
    {"image": "german/promoDE1.2/11_screenshot.png", "key": "*", "title": "Core — 1.2 Numbers & Time"},
    {"image": "german/promoDE1.2/12_screenshot.png", "key": "*", "title": "Core — 1.2 Numbers & Time"},
    {"image": "german/promoDE1.2/13_screenshot.png", "key": "*", "title": "Core — 1.2 Numbers & Time"},
    {"image": "german/promoDE1.2/14_screenshot.png", "key": "*", "title": "Core — 1.2 Numbers & Time"},
    {"image": "german/promoDE1.2/15_screenshot.png", "key": "*", "title": "Core — 1.2 Numbers & Time"},
    {"image": "german/promoDE1.2/16_screenshot.png", "key": "*", "title": "Core — 1.2 Numbers & Time"},
    {"image": "german/promoDE1.2/17_screenshot.png", "key": "*", "title": "Core — 1.2 Numbers & Time"},
    {"image": "german/promoDE1.2/18_screenshot.png", "key": "*", "title": "Core — 1.2 Numbers & Time"},
    {"image": "german/promoDE1.2/19_screenshot.png", "key": "*", "title": "Core — 1.2 Numbers & Time"},
    {"image": "german/promoDE1.2/20_screenshot.png", "key": "*", "title": "Core — 1.2 Numbers & Time"},
    {"image": "german/promoDE1.2/21_screenshot.png", "key": "*", "title": "Core — 1.2 Numbers & Time"},
    {"image": "german/promoDE1.2/22_screenshot.png", "key": "*", "title": "Core — 1.2 Numbers & Time"},
    {"image": "german/promoDE1.2/23_screenshot.png", "key": "*", "title": "Core — 1.2 Numbers & Time"},
    {"image": "german/promoDE1.2/24_screenshot.png", "key": "*", "title": "Core — 1.2 Numbers & Time"},
    {"image": "german/promoDE1.2/25_screenshot.png", "key": "*", "title": "Core — 1.2 Numbers & Time"},
    {"image": "german/promoDE1.2/26_screenshot.png", "key": "*", "title": "Core — 1.2 Numbers & Time"},
    {"image": "german/promoDE1.2/27_screenshot.png", "key": "*", "title": "Core — 1.2 Numbers & Time"},
    {"image": "german/promoDE1.2/28_screenshot.png", "key": "*", "title": "Core — 1.2 Numbers & Time"},
    {"image": "german/promoDE1.2/29_screenshot.png", "key": null, "title": "Core Complete", "end": true}
  ],
  "german-pareto1": [
    {"image": "german/promoDE7.3/30_screenshot.png", "key": "*", "title": "Pareto 1 — 7.3 Travel & Accommodation"},
    {"image": "german/promoDE7.3/31_screenshot.png", "key": "*", "title": "Pareto 1 — 7.3 Travel & Accommodation"},
    {"image": "german/promoDE7.3/32_screenshot.png", "key": "*", "title": "Pareto 1 — 7.3 Travel & Accommodation"},
    {"image": "german/promoDE7.3/33_screenshot.png", "key": "*", "title": "Pareto 1 — 7.3 Travel & Accommodation"},
    {"image": "german/promoDE7.3/34_screenshot.png", "key": "*", "title": "Pareto 1 — 7.3 Travel & Accommodation"},
    {"image": "german/promoDE7.3/35_screenshot.png", "key": "*", "title": "Pareto 1 — 7.3 Travel & Accommodation"},
    {"image": "german/promoDE7.3/36_screenshot.png", "key": "*", "title": "Pareto 1 — 7.3 Travel & Accommodation"},
    {"image": "german/promoDE7.3/37_screenshot.png", "key": "*", "title": "Pareto 1 — 7.3 Travel & Accommodation"},
    {"image": "german/promoDE7.3/38_screenshot.png", "key": "*", "title": "Pareto 1 — 7.3 Travel & Accommodation"},
    {"image": "german/promoDE7.3/39_screenshot.png", "key": "*", "title": "Pareto 1 — 7.3 Travel & Accommodation"},
    {"image": "german/promoDE7.3/40_screenshot.png", "key": "*", "title": "Pareto 1 — 7.3 Travel & Accommodation"},
    {"image": "german/promoDE7.3/41_screenshot.png", "key": "*", "title": "Pareto 1 — 7.3 Travel & Accommodation"},
    {"image": "german/promoDE7.3/42_screenshot.png", "key": "*", "title": "Pareto 1 — 7.3 Travel & Accommodation"},
    {"image": "german/promoDE7.3/43_screenshot.png", "key": "*", "title": "Pareto 1 — 7.3 Travel & Accommodation"},
    {"image": "german/promoDE7.3/44_screenshot.png", "key": "*", "title": "Pareto 1 — 7.3 Travel & Accommodation"},
    {"image": "german/promoDE7.3/45_screenshot.png", "key": "*", "title": "Pareto 1 — 7.3 Travel & Accommodation"},
    {"image": "german/promoDE7.3/46_screenshot.png", "key": "*", "title": "Pareto 1 — 7.3 Travel & Accommodation"},
    {"image": "german/promoDE7.3/47_screenshot.png", "key": "*", "title": "Pareto 1 — 7.3 Travel & Accommodation"},
    {"image": "german/promoDE7.3/48_screenshot.png", "key": "*", "title": "Pareto 1 — 7.3 Travel & Accommodation"},
    {"image": "german/promoDE7.3/49_screenshot.png", "key": "*", "title": "Pareto 1 — 7.3 Travel & Accommodation"},
    {"image": "german/promoDE7.3/50_screenshot.png", "key": "*", "title": "Pareto 1 — 7.3 Travel & Accommodation"},
    {"image": "german/promoDE7.3/51_screenshot.png", "key": "*", "title": "Pareto 1 — 7.3 Travel & Accommodation"},
    {"image": "german/promoDE7.3/52_screenshot.png", "key": "*", "title": "Pareto 1 — 7.3 Travel & Accommodation"},
    {"image": "german/promoDE7.3/53_screenshot.png", "key": "*", "title": "Pareto 1 — 7.3 Travel & Accommodation"},
    {"image": "german/promoDE7.3/54_screenshot.png", "key": "*", "title": "Pareto 1 — 7.3 Travel & Accommodation"},
    {"image": "german/promoDE7.3/55_screenshot.png", "key": "*", "title": "Pareto 1 — 7.3 Travel & Accommodation"},
    {"image": "german/promoDE7.3/56_screenshot.png", "key": "*", "title": "Pareto 1 — 7.3 Travel & Accommodation"},
    {"image": "german/promoDE7.3/57_screenshot.png", "key": "*", "title": "Pareto 1 — 7.3 Travel & Accommodation"},
    {"image": "german/promoDE7.3/58_screenshot.png", "key": null, "title": "Pareto 1 Complete", "end": true}
  ],
  "german-pareto2": [
    {"image": "german/promoDE13.7/59_screenshot.png", "key": "*", "title": "Pareto 2 — 13.7 Social Roles & People"},
    {"image": "german/promoDE13.7/60_screenshot.png", "key": "*", "title": "Pareto 2 — 13.7 Social Roles & People"},
    {"image": "german/promoDE13.7/61_screenshot.png", "key": "*", "title": "Pareto 2 — 13.7 Social Roles & People"},
    {"image": "german/promoDE13.7/62_screenshot.png", "key": "*", "title": "Pareto 2 — 13.7 Social Roles & People"},
    {"image": "german/promoDE13.7/63_screenshot.png", "key": "*", "title": "Pareto 2 — 13.7 Social Roles & People"},
    {"image": "german/promoDE13.7/64_screenshot.png", "key": "*", "title": "Pareto 2 — 13.7 Social Roles & People"},
    {"image": "german/promoDE13.7/65_screenshot.png", "key": "*", "title": "Pareto 2 — 13.7 Social Roles & People"},
    {"image": "german/promoDE13.7/66_screenshot.png", "key": "*", "title": "Pareto 2 — 13.7 Social Roles & People"},
    {"image": "german/promoDE13.7/67_screenshot.png", "key": "*", "title": "Pareto 2 — 13.7 Social Roles & People"},
    {"image": "german/promoDE13.7/68_screenshot.png", "key": "*", "title": "Pareto 2 — 13.7 Social Roles & People"},
    {"image": "german/promoDE13.7/69_screenshot.png", "key": "*", "title": "Pareto 2 — 13.7 Social Roles & People"},
    {"image": "german/promoDE13.7/70_screenshot.png", "key": "*", "title": "Pareto 2 — 13.7 Social Roles & People"},
    {"image": "german/promoDE13.7/71_screenshot.png", "key": "*", "title": "Pareto 2 — 13.7 Social Roles & People"},
    {"image": "german/promoDE13.7/72_screenshot.png", "key": "*", "title": "Pareto 2 — 13.7 Social Roles & People"},
    {"image": "german/promoDE13.7/73_screenshot.png", "key": "*", "title": "Pareto 2 — 13.7 Social Roles & People"},
    {"image": "german/promoDE13.7/74_screenshot.png", "key": "*", "title": "Pareto 2 — 13.7 Social Roles & People"},
    {"image": "german/promoDE13.7/75_screenshot.png", "key": "*", "title": "Pareto 2 — 13.7 Social Roles & People"},
    {"image": "german/promoDE13.7/76_screenshot.png", "key": "*", "title": "Pareto 2 — 13.7 Social Roles & People"},
    {"image": "german/promoDE13.7/77_screenshot.png", "key": "*", "title": "Pareto 2 — 13.7 Social Roles & People"},
    {"image": "german/promoDE13.7/78_screenshot.png", "key": "*", "title": "Pareto 2 — 13.7 Social Roles & People"},
    {"image": "german/promoDE13.7/79_screenshot.png", "key": "*", "title": "Pareto 2 — 13.7 Social Roles & People"},
    {"image": "german/promoDE13.7/80_screenshot.png", "key": "*", "title": "Pareto 2 — 13.7 Social Roles & People"},
    {"image": "german/promoDE13.7/81_screenshot.png", "key": "*", "title": "Pareto 2 — 13.7 Social Roles & People"},
    {"image": "german/promoDE13.7/82_screenshot.png", "key": "*", "title": "Pareto 2 — 13.7 Social Roles & People"},
    {"image": "german/promoDE13.7/83_screenshot.png", "key": "*", "title": "Pareto 2 — 13.7 Social Roles & People"},
    {"image": "german/promoDE13.7/84_screenshot.png", "key": "*", "title": "Pareto 2 — 13.7 Social Roles & People"},
    {"image": "german/promoDE13.7/85_screenshot.png", "key": "*", "title": "Pareto 2 — 13.7 Social Roles & People"},
    {"image": "german/promoDE13.7/86_screenshot.png", "key": "*", "title": "Pareto 2 — 13.7 Social Roles & People"},
    {"image": "german/promoDE13.7/87_screenshot.png", "key": "*", "title": "Pareto 2 — 13.7 Social Roles & People"},
    {"image": "german/promoDE13.7/88_screenshot.png", "key": "*", "title": "Pareto 2 — 13.7 Social Roles & People"},
    {"image": "german/promoDE13.7/89_screenshot.png", "key": "*", "title": "Pareto 2 — 13.7 Social Roles & People"},
    {"image": "german/promoDE13.7/90_screenshot.png", "key": "*", "title": "Pareto 2 — 13.7 Social Roles & People"},
    {"image": "german/promoDE13.7/91_screenshot.png", "key": "*", "title": "Pareto 2 — 13.7 Social Roles & People"},
    {"image": "german/promoDE13.7/92_screenshot.png", "key": "*", "title": "Pareto 2 — 13.7 Social Roles & People"},
    {"image": "german/promoDE13.7/93_screenshot.png", "key": "*", "title": "Pareto 2 — 13.7 Social Roles & People"},
    {"image": "german/promoDE13.7/94_screenshot.png", "key": "*", "title": "Pareto 2 — 13.7 Social Roles & People"},
    {"image": "german/promoDE13.7/95_screenshot.png", "key": "*", "title": "Pareto 2 — 13.7 Social Roles & People"},
    {"image": "german/promoDE13.7/96_screenshot.png", "key": "*", "title": "Pareto 2 — 13.7 Social Roles & People"},
    {"image": "german/promoDE13.7/97_screenshot.png", "key": null, "title": "Pareto 2 Complete", "end": true}
  ]
}
